mycliapp/__init__.py
mycliapp/main.py
mycliapper132-0.11.dist-info/METADATA
mycliapper132-0.11.dist-info/WHEEL
mycliapper132-0.11.dist-info/entry_points.txt
mycliapper132-0.11.dist-info/top_level.txt
mycliapper132-0.11.dist-info/RECORD
